curved/__init__.py
curved/_rustlib.cpython-310-x86_64-linux-gnu.so
curved-0.1.2.dist-info/WHEEL
curved-0.1.2.dist-info/LICENSE
curved-0.1.2.dist-info/METADATA
curved-0.1.2.dist-info/RECORD
curved-0.1.2.dist-info/top_level.txt
