Metadata-Version: 2.1
Name: curved
Version: 0.1.2
Summary: a high performance Python module for curve simplification
Home-page: https://github.com/ioces/curved
Author: Matthew Schubert
Author-email: ms-curved@ioces.com
License: MIT License
Platform: UNKNOWN
License-File: LICENSE
Requires-Dist: numpy
